{"id":"calculations;multiplying-numbers;chrome-119-0-6045-159;linux","name":"Multiplying numbers","title":"Multiplying numbers","manual":false,"testSteps":[{"number":1,"description":"Before","startTime":1701484129502,"children":[],"reportData":[],"screenshots":[],"duration":1,"result":"SUCCESS"},{"number":2,"description":"Given Callie decides to use the Super Calculator","startTime":1701484129503,"children":[{"number":3,"description":"Callie navigates to '/protractor-demo/'","startTime":1701484129504,"children":[],"reportData":[],"screenshots":[{"screenshot":"photo-linux-chrome-119.0.6045.159-callie-navigates-to-protractor-dem-6c520ed326.png","timeStamp":1701484129627}],"duration":48,"result":"SUCCESS"}],"reportData":[],"screenshots":[],"duration":132,"result":"SUCCESS"},{"number":4,"description":"When she multiplies 6 and 2","startTime":1701484129635,"children":[{"number":5,"description":"Callie enters a left operand of 6","startTime":1701484129649,"children":[{"number":6,"description":"Callie enters '6' into left operand input","startTime":1701484129650,"children":[],"reportData":[],"screenshots":[{"screenshot":"photo-linux-chrome-119.0.6045.159-callie-enters-6-into-left-operand-11779e2f8a.png","timeStamp":1701484129778}],"duration":60,"result":"SUCCESS"}],"reportData":[],"screenshots":[],"duration":133,"result":"SUCCESS"},{"number":7,"description":"Callie selects the * operator","startTime":1701484129792,"children":[{"number":8,"description":"Callie selects '*' from operator dropdown","startTime":1701484129793,"children":[],"reportData":[],"screenshots":[{"screenshot":"photo-linux-chrome-119.0.6045.159-callie-selects-from-operator-dro-eaa1c5f1be.png","timeStamp":1701484129912}],"duration":47,"result":"SUCCESS"}],"reportData":[],"screenshots":[],"duration":129,"result":"SUCCESS"},{"number":9,"description":"Callie enters a right operand of 2","startTime":1701484129931,"children":[{"number":10,"description":"Callie enters '2' into right operand input","startTime":1701484129931,"children":[],"reportData":[],"screenshots":[{"screenshot":"photo-linux-chrome-119.0.6045.159-callie-enters-2-into-right-operand-5b0801419b.png","timeStamp":1701484130062}],"duration":59,"result":"SUCCESS"}],"reportData":[],"screenshots":[],"duration":139,"result":"SUCCESS"},{"number":11,"description":"Callie confirms calculation","startTime":1701484130080,"children":[{"number":12,"description":"Callie clicks on \"Go\" button","startTime":1701484130080,"children":[],"reportData":[],"screenshots":[{"screenshot":"photo-linux-chrome-119.0.6045.159-callie-clicks-on-go-button-9788d7f7e0.png","timeStamp":1701484130246}],"duration":84,"result":"SUCCESS"}],"reportData":[],"screenshots":[],"duration":175,"result":"SUCCESS"}],"reportData":[],"screenshots":[],"duration":630,"result":"SUCCESS"},{"number":13,"description":"Then she should see that the result is 12","startTime":1701484130266,"children":[{"number":14,"description":"Callie ensures that the text of result does equal '12'","startTime":1701484130269,"children":[],"reportData":[],"screenshots":[{"screenshot":"photo-linux-chrome-119.0.6045.159-callie-ensures-that-the-text-of-resu-b55a569559.png","timeStamp":1701484132094}],"duration":1772,"result":"SUCCESS"}],"reportData":[],"screenshots":[],"duration":1836,"result":"SUCCESS"}],"userStory":{"id":"calculations","storyName":"Calculations","path":"features/super_calculator/calculations.feature","type":"feature","narrative":"In order to learn how to use Serenity/JS with Cucumber and Protractor\nAs a Curious Developer\nI'd like to see an example"},"startTime":1701484129502,"testSource":"Cucumber","tags":[{"name":"Super calculator","type":"capability","displayName":"Super calculator"},{"name":"Super calculator/Calculations","type":"feature","displayName":"Calculations"},{"name":"fast","type":"tag","displayName":"fast"},{"name":"smoke","type":"tag","displayName":"smoke"},{"name":"chrome 119.0.6045.159","type":"browser","browserName":"chrome","browserVersion":"119.0.6045.159","displayName":"chrome 119.0.6045.159"},{"name":"Linux","type":"platform","platformName":"Linux","platformVersion":"","displayName":"Linux"}],"featureTag":{"name":"Super calculator/Calculations","type":"feature","displayName":"Calculations"},"context":"chrome,linux","driver":"chrome","result":"SUCCESS","duration":2612}